django_article/__init__.py
django_article/admin.py
django_article/apps.py
django_article/consts.py
django_article/models.py
django_article/settings.py
django_article/tests.py
django_article/urls.py
django_article/migrations/__init__.py
django_article/static/css/article_detail.css
django_article/static/css/article_list.css
django_article/static/css/common.css
django_article/static/css/index.css
django_article/static/js/article_detail.js
django_article/static/js/article_list.js
django_article/static/js/common.js
django_article/static/js/index.js
django_article/static/lib/css/bootstrap-3.3.7.min.css
django_article/static/lib/css/bootstrap-theme-3.3.7.min.css
django_article/static/lib/css/bootstrap.min.css.map
django_article/static/lib/css/normalize-8.0.0.min.css
django_article/static/lib/css/toastr-2.1.3.min.css
django_article/static/lib/fonts/element-icons.ttf
django_article/static/lib/fonts/element-icons.woff
django_article/static/lib/fonts/glyphicons-halflings-regular.eot
django_article/static/lib/fonts/glyphicons-halflings-regular.svg
django_article/static/lib/fonts/glyphicons-halflings-regular.ttf
django_article/static/lib/fonts/glyphicons-halflings-regular.woff
django_article/static/lib/fonts/glyphicons-halflings-regular.woff2
django_article/static/lib/js/bootstrap-3.3.7.min.js
django_article/static/lib/js/html5shiv.min.js
django_article/static/lib/js/jquery-3.3.1.min.js
django_article/static/lib/js/toastr-2.1.3.min.js
django_article/static/lib/js/toastr.js.map
django_article/static/lib/js/vue-2.5.13.min.js
django_article/static/lib/js/vue-lazyload-1.2.3.js
django_article/templates/django_article/article/article_detail.html
django_article/templates/django_article/article/article_list.html
django_article/templates/django_article/home/index.html
django_article/templates/django_article/layout/base.html
django_article/templates/django_article/layout/header.html
django_article/views/__init__.py
django_article/views/api.py
django_article-0.1.2.dist-info/METADATA
django_article-0.1.2.dist-info/RECORD
django_article-0.1.2.dist-info/WHEEL
django_article-0.1.2.dist-info/top_level.txt
